setup.py
tamaster/__init__.py
tamaster/_version.py
tamaster.egg-info/PKG-INFO
tamaster.egg-info/SOURCES.txt
tamaster.egg-info/dependency_links.txt
tamaster.egg-info/requires.txt
tamaster.egg-info/top_level.txt
tamaster/base/__init__.py
tamaster/custodian/__init__.py
tamaster/custodian/china_merchants_securities.py
tamaster/custodian/citic_securities.py
tamaster/custodian/gtja_securities.py
tamaster/custodian/guosen_securities.py
tamaster/data/__init__.py
tamaster/data/bank_account.py
tamaster/data/fund.py
tamaster/data/investor.py
tamaster/data/transaction.py