Metadata-Version: 1.0
Name: tamaster
Version: 0.0.1
Summary: TA data interface implementation
Home-page: UNKNOWN
Author: puyuantech
Author-email: info@puyuan.tech
License: UNKNOWN
Platform: UNKNOWN
